src/PyQtSerializer.py
src/Serialize.py
src/Serializer.py
src/__init__.py
src/utils.py
PyQtSerializer-0.0.13.dist-info/METADATA
PyQtSerializer-0.0.13.dist-info/WHEEL
PyQtSerializer-0.0.13.dist-info/top_level.txt
PyQtSerializer-0.0.13.dist-info/RECORD
