Metadata-Version: 2.1
Name: PyQtSerializer
Version: 0.0.13
Summary: A PyQt Serialization Library
Author: Ahmed Essam (https://github.com/Were-Logan-0110)
Author-email: <headnuts92@gmail.com>
Keywords: python,encryption,serialize,serialization,pickle,pyqt,qtsave
Classifier: Development Status :: 4 - Beta
Classifier: Intended Audience :: Developers
Classifier: Programming Language :: Python :: 3
Classifier: Operating System :: Unix
Classifier: Operating System :: MacOS :: MacOS X
Classifier: Operating System :: Microsoft :: Windows
Requires-Dist: qtpy
Requires-Dist: pycryptodome
